setup.py
ez_probability/Binomialdistribution.py
ez_probability/Gaussiandistribution.py
ez_probability/Generaldistribution.py
ez_probability/__init__.py
ez_probability.egg-info/PKG-INFO
ez_probability.egg-info/SOURCES.txt
ez_probability.egg-info/dependency_links.txt
ez_probability.egg-info/not-zip-safe
ez_probability.egg-info/top_level.txt