Metadata-Version: 1.0
Name: ez-probability
Version: 1.0
Summary: Binomial & Gaussian distributions from the course "AI Programming with Python" by Udacity
Home-page: UNKNOWN
Author: UNKNOWN
Author-email: UNKNOWN
License: UNKNOWN
Platform: UNKNOWN
